gofish/__init__.py
gofish/annulus.py
gofish/gofish.py
gofish-1.2.2.dist-info/LICENSE.md
gofish-1.2.2.dist-info/METADATA
gofish-1.2.2.dist-info/WHEEL
gofish-1.2.2.dist-info/top_level.txt
gofish-1.2.2.dist-info/RECORD
