Metadata-Version: 2.1
Name: gofish
Version: 1.2.2
Summary: Fishing for molecular line emission in protoplanetary disks.
Home-page: https://github.com/richteague/gofish
Author: Richard Teague
Author-email: richard.d.teague@cfa.harvard.edu
License: UNKNOWN
Platform: UNKNOWN
Classifier: Programming Language :: Python :: 3
Classifier: License :: OSI Approved :: MIT License
Classifier: Operating System :: OS Independent
Requires-Dist: numpy
Requires-Dist: astropy
Requires-Dist: scipy
